[
  {
    "MessageID": "AAMkAGUzODYyY2VhLWI4MGYtNDJiNC1hYWQyLTI2OGY1MmI4OTRhZgBGAAAAAAD2xIHfYeghS7NTr5D79J_KBwCpc6rLDJ0XTqvTzc3Yp-jsAAAAAAEKAACpc6rLDJ0XTqvTzc3Yp-jsAALbV9KKAAA=",
    "Subject": "Sales EDI PO UPLOAD Alert (US)",
    "SenderEmail": "b2b@synnex.com",
    "SenderName": "B2B",
    "Recipients": "{\"to\": [\"team4401@tdsynnex.com\"], \"cc\": []}",
    "ReceivedTime": "2025-04-16T15:05:21Z",
    "FolderPath": "Deleted Items",
    "BodyText": "[External E-mail] CAUTION: This email originated from outside of the organization. Do not click links or open attachments unless you recognize the sender and know the content is safe.\r\n\r\n\r\n                         \r\n ----------------------- \r\n **CUST850 NOT UPLOADED: \r\n\r\n tp_name          created                        alert_desc                                                                       \r\n ---------------- ------------------------------ -------------------------------------------------------------------------------- \r\n CDK GLOBAL LLC   04/16 06:05                    CUST850 NOT UPLOADED:TP NAME-CDK GLOBAL LLCPO#-~2151887                          \r\n HITACHI AMERICA  04/15 10:05                    CUST850 NOT UPLOADED:TP NAME-HITACHI AMERICA LTDPO#-~396568                      \r\n TRIMEGA          04/14 13:05                    CUST850 NOT UPLOADED:TP NAME-TRIMEGAPO#-~56592                                   \r\n HITACHI AMERICA  04/13 16:05                    CUST850 NOT UPLOADED:TP NAME-HITACHI AMERICA LTDPO#-~396564                      \r\n\r\n                     \r\n ------------------- \r\n **NO 856 GENERATED: \r\n\r\n tp_name          created                        alert_desc                                                                       \r\n ---------------- ------------------------------ -------------------------------------------------------------------------------- \r\n CDW856           04/16 03:35                    NO 856 GENERATED:57371~order_no 158927857                                        \r\n CDW856           04/16 03:35                    NO 856 GENERATED:57371~order_no 159202436                                        \r\n CDW856           04/16 03:35                    NO 856 GENERATED:57371~order_no 160043211                                        \r\n CDW856           04/16 03:35                    NO 856 GENERATED:57371~order_no 160050828                                        \r\n[... content truncated for analysis ...]",
    "HasAttachments": 0,
    "Importance": "normal",
    "MailboxSource": "Team4401@TDSynnex.com",
    "ThreadID": "AAQkAGUzODYyY2VhLWI4MGYtNDJiNC1hYWQyLTI2OGY1MmI4OTRhZgAQAKIZAkqXbrJOqbJ6-LAgcfo=",
    "ConversationID": "",
    "BodyHTML": null,
    "IsRead": 0,
    "ExtractedAt": "2025-05-21T11:52:21.143999",
    "AnalyzedAt": null,
    "SuggestedThemes": null,
    "SuggestedCategory": null,
    "KeyPhrases": null,
    "FullAnalysis": null,
    "IsSynthetic": 0,
    "workflow_state": null
  },
  {
    "MessageID": "AAMkAGUzODYyY2VhLWI4MGYtNDJiNC1hYWQyLTI2OGY1MmI4OTRhZgBGAAAAAAD2xIHfYeghS7NTr5D79J_KBwCpc6rLDJ0XTqvTzc3Yp-jsAAAAAAEKAACpc6rLDJ0XTqvTzc3Yp-jsAALbV9KJAAA=",
    "Subject": "Sales EDI PO UPLOAD Alert (US)",
    "SenderEmail": "b2b@synnex.com",
    "SenderName": "B2B",
    "Recipients": "{\"to\": [\"team4401@tdsynnex.com\"], \"cc\": []}",
    "ReceivedTime": "2025-04-16T14:35:16Z",
    "FolderPath": "Deleted Items",
    "BodyText": "[External E-mail] CAUTION: This email originated from outside of the organization. Do not click links or open attachments unless you recognize the sender and know the content is safe.\r\n\r\n\r\n                         \r\n ----------------------- \r\n **CUST850 NOT UPLOADED: \r\n\r\n tp_name          created                        alert_desc                                                                       \r\n ---------------- ------------------------------ -------------------------------------------------------------------------------- \r\n CDK GLOBAL LLC   04/16 06:05                    CUST850 NOT UPLOADED:TP NAME-CDK GLOBAL LLCPO#-~2151887                          \r\n HITACHI AMERICA  04/15 10:05                    CUST850 NOT UPLOADED:TP NAME-HITACHI AMERICA LTDPO#-~396568                      \r\n TRIMEGA          04/14 13:05                    CUST850 NOT UPLOADED:TP NAME-TRIMEGAPO#-~56592                                   \r\n HITACHI AMERICA  04/13 16:05                    CUST850 NOT UPLOADED:TP NAME-HITACHI AMERICA LTDPO#-~396564                      \r\n\r\n                     \r\n ------------------- \r\n **NO 856 GENERATED: \r\n\r\n tp_name          created                        alert_desc                                                                       \r\n ---------------- ------------------------------ -------------------------------------------------------------------------------- \r\n CDW856           04/16 03:35                    NO 856 GENERATED:57371~order_no 158927857                                        \r\n CDW856           04/16 03:35                    NO 856 GENERATED:57371~order_no 159202436                                        \r\n CDW856           04/16 03:35                    NO 856 GENERATED:57371~order_no 160043211                                        \r\n CDW856           04/16 03:35                    NO 856 GENERATED:57371~order_no 160050828                                        \r\n[... content truncated for analysis ...]",
    "HasAttachments": 0,
    "Importance": "normal",
    "MailboxSource": "Team4401@TDSynnex.com",
    "ThreadID": "AAQkAGUzODYyY2VhLWI4MGYtNDJiNC1hYWQyLTI2OGY1MmI4OTRhZgAQAOSMSpQLp-pMsmZN8kdF47o=",
    "ConversationID": "",
    "BodyHTML": null,
    "IsRead": 0,
    "ExtractedAt": "2025-05-21T11:52:21.152616",
    "AnalyzedAt": null,
    "SuggestedThemes": null,
    "SuggestedCategory": null,
    "KeyPhrases": null,
    "FullAnalysis": null,
    "IsSynthetic": 0,
    "workflow_state": null
  },
  {
    "MessageID": "AAMkAGUzODYyY2VhLWI4MGYtNDJiNC1hYWQyLTI2OGY1MmI4OTRhZgBGAAAAAAD2xIHfYeghS7NTr5D79J_KBwCpc6rLDJ0XTqvTzc3Yp-jsAAAAAAEKAACpc6rLDJ0XTqvTzc3Yp-jsAALbV9KIAAA=",
    "Subject": "Sales EDI PO UPLOAD Alert (US)",
    "SenderEmail": "b2b@synnex.com",
    "SenderName": "B2B",
    "Recipients": "{\"to\": [\"team4401@tdsynnex.com\"], \"cc\": []}",
    "ReceivedTime": "2025-04-16T14:05:14Z",
    "FolderPath": "Deleted Items",
    "BodyText": "[External E-mail] CAUTION: This email originated from outside of the organization. Do not click links or open attachments unless you recognize the sender and know the content is safe.\r\n\r\n\r\n                         \r\n ----------------------- \r\n **CUST850 NOT UPLOADED: \r\n\r\n tp_name          created                        alert_desc                                                                       \r\n ---------------- ------------------------------ -------------------------------------------------------------------------------- \r\n CDK GLOBAL LLC   04/16 06:05                    CUST850 NOT UPLOADED:TP NAME-CDK GLOBAL LLCPO#-~2151887                          \r\n HITACHI AMERICA  04/15 10:05                    CUST850 NOT UPLOADED:TP NAME-HITACHI AMERICA LTDPO#-~396568                      \r\n TRIMEGA          04/14 13:05                    CUST850 NOT UPLOADED:TP NAME-TRIMEGAPO#-~56592                                   \r\n HITACHI AMERICA  04/13 16:05                    CUST850 NOT UPLOADED:TP NAME-HITACHI AMERICA LTDPO#-~396564                      \r\n\r\n                     \r\n ------------------- \r\n **NO 856 GENERATED: \r\n\r\n tp_name          created                        alert_desc                                                                       \r\n ---------------- ------------------------------ -------------------------------------------------------------------------------- \r\n CDW856           04/16 03:35                    NO 856 GENERATED:57371~order_no 158927857                                        \r\n CDW856           04/16 03:35                    NO 856 GENERATED:57371~order_no 159202436                                        \r\n CDW856           04/16 03:35                    NO 856 GENERATED:57371~order_no 160043211                                        \r\n CDW856           04/16 03:35                    NO 856 GENERATED:57371~order_no 160050828                                        \r\n[... content truncated for analysis ...]",
    "HasAttachments": 0,
    "Importance": "normal",
    "MailboxSource": "Team4401@TDSynnex.com",
    "ThreadID": "AAQkAGUzODYyY2VhLWI4MGYtNDJiNC1hYWQyLTI2OGY1MmI4OTRhZgAQAMzW6FBSs9lOpelWvgGPd7g=",
    "ConversationID": "",
    "BodyHTML": null,
    "IsRead": 0,
    "ExtractedAt": "2025-05-21T11:52:21.161090",
    "AnalyzedAt": null,
    "SuggestedThemes": null,
    "SuggestedCategory": null,
    "KeyPhrases": null,
    "FullAnalysis": null,
    "IsSynthetic": 0,
    "workflow_state": null
  },
  {
    "MessageID": "AAMkAGUzODYyY2VhLWI4MGYtNDJiNC1hYWQyLTI2OGY1MmI4OTRhZgBGAAAAAAD2xIHfYeghS7NTr5D79J_KBwCpc6rLDJ0XTqvTzc3Yp-jsAAAAAAEKAACpc6rLDJ0XTqvTzc3Yp-jsAALbV9KHAAA=",
    "Subject": "Sales EDI PO UPLOAD Alert (US)",
    "SenderEmail": "b2b@synnex.com",
    "SenderName": "B2B",
    "Recipients": "{\"to\": [\"team4401@tdsynnex.com\"], \"cc\": []}",
    "ReceivedTime": "2025-04-16T13:35:14Z",
    "FolderPath": "Deleted Items",
    "BodyText": "[External E-mail] CAUTION: This email originated from outside of the organization. Do not click links or open attachments unless you recognize the sender and know the content is safe.\r\n\r\n\r\n                         \r\n ----------------------- \r\n **CUST850 NOT UPLOADED: \r\n\r\n tp_name          created                        alert_desc                                                                       \r\n ---------------- ------------------------------ -------------------------------------------------------------------------------- \r\n CDK GLOBAL LLC   04/16 06:05                    CUST850 NOT UPLOADED:TP NAME-CDK GLOBAL LLCPO#-~2151887                          \r\n HITACHI AMERICA  04/15 10:05                    CUST850 NOT UPLOADED:TP NAME-HITACHI AMERICA LTDPO#-~396568                      \r\n TRIMEGA          04/14 13:05                    CUST850 NOT UPLOADED:TP NAME-TRIMEGAPO#-~56592                                   \r\n HITACHI AMERICA  04/13 16:05                    CUST850 NOT UPLOADED:TP NAME-HITACHI AMERICA LTDPO#-~396564                      \r\n\r\n                     \r\n ------------------- \r\n **NO 856 GENERATED: \r\n\r\n tp_name          created                        alert_desc                                                                       \r\n ---------------- ------------------------------ -------------------------------------------------------------------------------- \r\n CDW856           04/16 03:35                    NO 856 GENERATED:57371~order_no 158927857                                        \r\n CDW856           04/16 03:35                    NO 856 GENERATED:57371~order_no 159202436                                        \r\n CDW856           04/16 03:35                    NO 856 GENERATED:57371~order_no 160043211                                        \r\n CDW856           04/16 03:35                    NO 856 GENERATED:57371~order_no 160050828                                        \r\n[... content truncated for analysis ...]",
    "HasAttachments": 0,
    "Importance": "normal",
    "MailboxSource": "Team4401@TDSynnex.com",
    "ThreadID": "AAQkAGUzODYyY2VhLWI4MGYtNDJiNC1hYWQyLTI2OGY1MmI4OTRhZgAQALilOFXzy-NIiQOCHRMI7_Y=",
    "ConversationID": "",
    "BodyHTML": null,
    "IsRead": 0,
    "ExtractedAt": "2025-05-21T11:52:21.168981",
    "AnalyzedAt": null,
    "SuggestedThemes": null,
    "SuggestedCategory": null,
    "KeyPhrases": null,
    "FullAnalysis": null,
    "IsSynthetic": 0,
    "workflow_state": null
  },
  {
    "MessageID": "AAMkAGUzODYyY2VhLWI4MGYtNDJiNC1hYWQyLTI2OGY1MmI4OTRhZgBGAAAAAAD2xIHfYeghS7NTr5D79J_KBwCpc6rLDJ0XTqvTzc3Yp-jsAAAAAAEKAACpc6rLDJ0XTqvTzc3Yp-jsAALbV9KGAAA=",
    "Subject": "Sales EDI PO UPLOAD Alert (US)",
    "SenderEmail": "b2b@synnex.com",
    "SenderName": "B2B",
    "Recipients": "{\"to\": [\"team4401@tdsynnex.com\"], \"cc\": []}",
    "ReceivedTime": "2025-04-16T12:05:16Z",
    "FolderPath": "Deleted Items",
    "BodyText": "[External E-mail] CAUTION: This email originated from outside of the organization. Do not click links or open attachments unless you recognize the sender and know the content is safe.\r\n\r\n\r\n                         \r\n ----------------------- \r\n **CUST850 NOT UPLOADED: \r\n\r\n tp_name          created                        alert_desc                                                                       \r\n ---------------- ------------------------------ -------------------------------------------------------------------------------- \r\n HITACHI AMERICA  04/15 10:05                    CUST850 NOT UPLOADED:TP NAME-HITACHI AMERICA LTDPO#-~396568                      \r\n TRIMEGA          04/14 13:05                    CUST850 NOT UPLOADED:TP NAME-TRIMEGAPO#-~56592                                   \r\n HITACHI AMERICA  04/13 16:05                    CUST850 NOT UPLOADED:TP NAME-HITACHI AMERICA LTDPO#-~396564                      \r\n\r\n                     \r\n ------------------- \r\n **NO 856 GENERATED: \r\n\r\n tp_name          created                        alert_desc                                                                       \r\n ---------------- ------------------------------ -------------------------------------------------------------------------------- \r\n CDW856           04/16 03:35                    NO 856 GENERATED:57371~order_no 158927857                                        \r\n CDW856           04/16 03:35                    NO 856 GENERATED:57371~order_no 159202436                                        \r\n CDW856           04/16 03:35                    NO 856 GENERATED:57371~order_no 160043211                                        \r\n CDW856           04/16 03:35                    NO 856 GENERATED:57371~order_no 160050828                                        \r\n CDW856           04/16 03:35                    NO 856 GENERATED:57371~order_no 160074014                                        \r\n[... content truncated for analysis ...]",
    "HasAttachments": 0,
    "Importance": "normal",
    "MailboxSource": "Team4401@TDSynnex.com",
    "ThreadID": "AAQkAGUzODYyY2VhLWI4MGYtNDJiNC1hYWQyLTI2OGY1MmI4OTRhZgAQABXoNLdvf5dEkW9MOu15rbA=",
    "ConversationID": "",
    "BodyHTML": null,
    "IsRead": 0,
    "ExtractedAt": "2025-05-21T11:52:21.177502",
    "AnalyzedAt": null,
    "SuggestedThemes": null,
    "SuggestedCategory": null,
    "KeyPhrases": null,
    "FullAnalysis": null,
    "IsSynthetic": 0,
    "workflow_state": null
  },
  {
    "MessageID": "AAMkAGUzODYyY2VhLWI4MGYtNDJiNC1hYWQyLTI2OGY1MmI4OTRhZgBGAAAAAAD2xIHfYeghS7NTr5D79J_KBwCpc6rLDJ0XTqvTzc3Yp-jsAAAAAAEKAACpc6rLDJ0XTqvTzc3Yp-jsAALbV9KFAAA=",
    "Subject": "Sales EDI PO UPLOAD Alert (US)",
    "SenderEmail": "b2b@synnex.com",
    "SenderName": "B2B",
    "Recipients": "{\"to\": [\"team4401@tdsynnex.com\"], \"cc\": []}",
    "ReceivedTime": "2025-04-16T11:05:11Z",
    "FolderPath": "Deleted Items",
    "BodyText": "[External E-mail] CAUTION: This email originated from outside of the organization. Do not click links or open attachments unless you recognize the sender and know the content is safe.\r\n\r\n\r\n                         \r\n ----------------------- \r\n **CUST850 NOT UPLOADED: \r\n\r\n tp_name          created                        alert_desc                                                                       \r\n ---------------- ------------------------------ -------------------------------------------------------------------------------- \r\n HITACHI AMERICA  04/15 10:05                    CUST850 NOT UPLOADED:TP NAME-HITACHI AMERICA LTDPO#-~396568                      \r\n TRIMEGA          04/14 13:05                    CUST850 NOT UPLOADED:TP NAME-TRIMEGAPO#-~56592                                   \r\n HITACHI AMERICA  04/13 16:05                    CUST850 NOT UPLOADED:TP NAME-HITACHI AMERICA LTDPO#-~396564                      \r\n\r\n                     \r\n ------------------- \r\n **NO 856 GENERATED: \r\n\r\n tp_name          created                        alert_desc                                                                       \r\n ---------------- ------------------------------ -------------------------------------------------------------------------------- \r\n CDW856           04/16 03:35                    NO 856 GENERATED:57371~order_no 158927857                                        \r\n CDW856           04/16 03:35                    NO 856 GENERATED:57371~order_no 159202436                                        \r\n CDW856           04/16 03:35                    NO 856 GENERATED:57371~order_no 160043211                                        \r\n CDW856           04/16 03:35                    NO 856 GENERATED:57371~order_no 160050828                                        \r\n CDW856           04/16 03:35                    NO 856 GENERATED:57371~order_no 160074014                                        \r\n[... content truncated for analysis ...]",
    "HasAttachments": 0,
    "Importance": "normal",
    "MailboxSource": "Team4401@TDSynnex.com",
    "ThreadID": "AAQkAGUzODYyY2VhLWI4MGYtNDJiNC1hYWQyLTI2OGY1MmI4OTRhZgAQAPby7v4CVntIkWCOCYEmMgc=",
    "ConversationID": "",
    "BodyHTML": null,
    "IsRead": 0,
    "ExtractedAt": "2025-05-21T11:52:21.185737",
    "AnalyzedAt": null,
    "SuggestedThemes": null,
    "SuggestedCategory": null,
    "KeyPhrases": null,
    "FullAnalysis": null,
    "IsSynthetic": 0,
    "workflow_state": null
  },
  {
    "MessageID": "AAMkAGUzODYyY2VhLWI4MGYtNDJiNC1hYWQyLTI2OGY1MmI4OTRhZgBGAAAAAAD2xIHfYeghS7NTr5D79J_KBwCpc6rLDJ0XTqvTzc3Yp-jsAAAAAAEKAACpc6rLDJ0XTqvTzc3Yp-jsAALbV9KEAAA=",
    "Subject": "Sales EDI PO UPLOAD Alert (US)",
    "SenderEmail": "b2b@synnex.com",
    "SenderName": "B2B",
    "Recipients": "{\"to\": [\"team4401@tdsynnex.com\"], \"cc\": []}",
    "ReceivedTime": "2025-04-16T10:35:15Z",
    "FolderPath": "Deleted Items",
    "BodyText": "[External E-mail] CAUTION: This email originated from outside of the organization. Do not click links or open attachments unless you recognize the sender and know the content is safe.\r\n\r\n\r\n                         \r\n ----------------------- \r\n **CUST850 NOT UPLOADED: \r\n\r\n tp_name          created                        alert_desc                                                                       \r\n ---------------- ------------------------------ -------------------------------------------------------------------------------- \r\n HITACHI AMERICA  04/15 10:05                    CUST850 NOT UPLOADED:TP NAME-HITACHI AMERICA LTDPO#-~396568                      \r\n TRIMEGA          04/14 13:05                    CUST850 NOT UPLOADED:TP NAME-TRIMEGAPO#-~56592                                   \r\n HITACHI AMERICA  04/13 16:05                    CUST850 NOT UPLOADED:TP NAME-HITACHI AMERICA LTDPO#-~396564                      \r\n\r\n                     \r\n ------------------- \r\n **NO 856 GENERATED: \r\n\r\n tp_name          created                        alert_desc                                                                       \r\n ---------------- ------------------------------ -------------------------------------------------------------------------------- \r\n CDW856           04/15 03:35                    NO 856 GENERATED:57371~order_no 157123618                                        \r\n CDW856           04/15 03:35                    NO 856 GENERATED:57371~order_no 158020556                                        \r\n CDW856           04/15 03:35                    NO 856 GENERATED:57371~order_no 158070555                                        \r\n CDW856           04/15 03:35                    NO 856 GENERATED:57371~order_no 159211116                                        \r\n CDW856           04/15 03:35                    NO 856 GENERATED:57371~order_no 159897126                                        \r\n[... content truncated for analysis ...]",
    "HasAttachments": 0,
    "Importance": "normal",
    "MailboxSource": "Team4401@TDSynnex.com",
    "ThreadID": "AAQkAGUzODYyY2VhLWI4MGYtNDJiNC1hYWQyLTI2OGY1MmI4OTRhZgAQAPi2UNO_FI5CrhlUt-YQr_s=",
    "ConversationID": "",
    "BodyHTML": null,
    "IsRead": 0,
    "ExtractedAt": "2025-05-21T11:52:21.195694",
    "AnalyzedAt": null,
    "SuggestedThemes": null,
    "SuggestedCategory": null,
    "KeyPhrases": null,
    "FullAnalysis": null,
    "IsSynthetic": 0,
    "workflow_state": null
  },
  {
    "MessageID": "AAMkAGUzODYyY2VhLWI4MGYtNDJiNC1hYWQyLTI2OGY1MmI4OTRhZgBGAAAAAAD2xIHfYeghS7NTr5D79J_KBwCpc6rLDJ0XTqvTzc3Yp-jsAAAAAAEKAACpc6rLDJ0XTqvTzc3Yp-jsAALbV9KDAAA=",
    "Subject": "Sales EDI PO UPLOAD Alert (US)",
    "SenderEmail": "b2b@synnex.com",
    "SenderName": "B2B",
    "Recipients": "{\"to\": [\"team4401@tdsynnex.com\"], \"cc\": []}",
    "ReceivedTime": "2025-04-16T09:35:18Z",
    "FolderPath": "Deleted Items",
    "BodyText": "[External E-mail] CAUTION: This email originated from outside of the organization. Do not click links or open attachments unless you recognize the sender and know the content is safe.\r\n\r\n\r\n                         \r\n ----------------------- \r\n **CUST850 NOT UPLOADED: \r\n\r\n tp_name          created                        alert_desc                                                                       \r\n ---------------- ------------------------------ -------------------------------------------------------------------------------- \r\n HITACHI AMERICA  04/15 10:05                    CUST850 NOT UPLOADED:TP NAME-HITACHI AMERICA LTDPO#-~396568                      \r\n TRIMEGA          04/14 13:05                    CUST850 NOT UPLOADED:TP NAME-TRIMEGAPO#-~56592                                   \r\n HITACHI AMERICA  04/13 16:05                    CUST850 NOT UPLOADED:TP NAME-HITACHI AMERICA LTDPO#-~396564                      \r\n\r\n                     \r\n ------------------- \r\n **NO 856 GENERATED: \r\n\r\n tp_name          created                        alert_desc                                                                       \r\n ---------------- ------------------------------ -------------------------------------------------------------------------------- \r\n CDW856           04/15 03:35                    NO 856 GENERATED:57371~order_no 157123618                                        \r\n CDW856           04/15 03:35                    NO 856 GENERATED:57371~order_no 158020556                                        \r\n CDW856           04/15 03:35                    NO 856 GENERATED:57371~order_no 158070555                                        \r\n CDW856           04/15 03:35                    NO 856 GENERATED:57371~order_no 159211116                                        \r\n CDW856           04/15 03:35                    NO 856 GENERATED:57371~order_no 159897126                                        \r\n[... content truncated for analysis ...]",
    "HasAttachments": 0,
    "Importance": "normal",
    "MailboxSource": "Team4401@TDSynnex.com",
    "ThreadID": "AAQkAGUzODYyY2VhLWI4MGYtNDJiNC1hYWQyLTI2OGY1MmI4OTRhZgAQACLdVIVyyXJInt7NtOhxgSc=",
    "ConversationID": "",
    "BodyHTML": null,
    "IsRead": 0,
    "ExtractedAt": "2025-05-21T11:52:21.202474",
    "AnalyzedAt": null,
    "SuggestedThemes": null,
    "SuggestedCategory": null,
    "KeyPhrases": null,
    "FullAnalysis": null,
    "IsSynthetic": 0,
    "workflow_state": null
  },
  {
    "MessageID": "AAMkAGUzODYyY2VhLWI4MGYtNDJiNC1hYWQyLTI2OGY1MmI4OTRhZgBGAAAAAAD2xIHfYeghS7NTr5D79J_KBwCpc6rLDJ0XTqvTzc3Yp-jsAAAAAAEKAACpc6rLDJ0XTqvTzc3Yp-jsAALbV9KCAAA=",
    "Subject": "Sales EDI PO UPLOAD Alert (US)",
    "SenderEmail": "b2b@synnex.com",
    "SenderName": "B2B",
    "Recipients": "{\"to\": [\"team4401@tdsynnex.com\"], \"cc\": []}",
    "ReceivedTime": "2025-04-16T09:05:13Z",
    "FolderPath": "Deleted Items",
    "BodyText": "[External E-mail] CAUTION: This email originated from outside of the organization. Do not click links or open attachments unless you recognize the sender and know the content is safe.\r\n\r\n\r\n                         \r\n ----------------------- \r\n **CUST850 NOT UPLOADED: \r\n\r\n tp_name          created                        alert_desc                                                                       \r\n ---------------- ------------------------------ -------------------------------------------------------------------------------- \r\n HITACHI AMERICA  04/15 10:05                    CUST850 NOT UPLOADED:TP NAME-HITACHI AMERICA LTDPO#-~396568                      \r\n TRIMEGA          04/14 13:05                    CUST850 NOT UPLOADED:TP NAME-TRIMEGAPO#-~56592                                   \r\n HITACHI AMERICA  04/13 16:05                    CUST850 NOT UPLOADED:TP NAME-HITACHI AMERICA LTDPO#-~396564                      \r\n\r\n                     \r\n ------------------- \r\n **NO 856 GENERATED: \r\n\r\n tp_name          created                        alert_desc                                                                       \r\n ---------------- ------------------------------ -------------------------------------------------------------------------------- \r\n CDW856           04/15 03:35                    NO 856 GENERATED:57371~order_no 157123618                                        \r\n CDW856           04/15 03:35                    NO 856 GENERATED:57371~order_no 158020556                                        \r\n CDW856           04/15 03:35                    NO 856 GENERATED:57371~order_no 158070555                                        \r\n CDW856           04/15 03:35                    NO 856 GENERATED:57371~order_no 159211116                                        \r\n CDW856           04/15 03:35                    NO 856 GENERATED:57371~order_no 159897126                                        \r\n[... content truncated for analysis ...]",
    "HasAttachments": 0,
    "Importance": "normal",
    "MailboxSource": "Team4401@TDSynnex.com",
    "ThreadID": "AAQkAGUzODYyY2VhLWI4MGYtNDJiNC1hYWQyLTI2OGY1MmI4OTRhZgAQABaYoAy6DYNBpm_kXgrYHXo=",
    "ConversationID": "",
    "BodyHTML": null,
    "IsRead": 0,
    "ExtractedAt": "2025-05-21T11:52:21.209345",
    "AnalyzedAt": null,
    "SuggestedThemes": null,
    "SuggestedCategory": null,
    "KeyPhrases": null,
    "FullAnalysis": null,
    "IsSynthetic": 0,
    "workflow_state": null
  },
  {
    "MessageID": "AAMkAGUzODYyY2VhLWI4MGYtNDJiNC1hYWQyLTI2OGY1MmI4OTRhZgBGAAAAAAD2xIHfYeghS7NTr5D79J_KBwCpc6rLDJ0XTqvTzc3Yp-jsAAAAAAEKAACpc6rLDJ0XTqvTzc3Yp-jsAALbV9KBAAA=",
    "Subject": "Sales EDI PO UPLOAD Alert (US)",
    "SenderEmail": "b2b@synnex.com",
    "SenderName": "B2B",
    "Recipients": "{\"to\": [\"team4401@tdsynnex.com\"], \"cc\": []}",
    "ReceivedTime": "2025-04-16T08:05:12Z",
    "FolderPath": "Deleted Items",
    "BodyText": "[External E-mail] CAUTION: This email originated from outside of the organization. Do not click links or open attachments unless you recognize the sender and know the content is safe.\r\n\r\n\r\n                         \r\n ----------------------- \r\n **CUST850 NOT UPLOADED: \r\n\r\n tp_name          created                        alert_desc                                                                       \r\n ---------------- ------------------------------ -------------------------------------------------------------------------------- \r\n HITACHI AMERICA  04/15 10:05                    CUST850 NOT UPLOADED:TP NAME-HITACHI AMERICA LTDPO#-~396568                      \r\n TRIMEGA          04/14 13:05                    CUST850 NOT UPLOADED:TP NAME-TRIMEGAPO#-~56592                                   \r\n HITACHI AMERICA  04/13 16:05                    CUST850 NOT UPLOADED:TP NAME-HITACHI AMERICA LTDPO#-~396564                      \r\n\r\n                     \r\n ------------------- \r\n **NO 856 GENERATED: \r\n\r\n tp_name          created                        alert_desc                                                                       \r\n ---------------- ------------------------------ -------------------------------------------------------------------------------- \r\n CDW856           04/15 03:35                    NO 856 GENERATED:57371~order_no 157123618                                        \r\n CDW856           04/15 03:35                    NO 856 GENERATED:57371~order_no 158020556                                        \r\n CDW856           04/15 03:35                    NO 856 GENERATED:57371~order_no 158070555                                        \r\n CDW856           04/15 03:35                    NO 856 GENERATED:57371~order_no 159211116                                        \r\n CDW856           04/15 03:35                    NO 856 GENERATED:57371~order_no 159897126                                        \r\n[... content truncated for analysis ...]",
    "HasAttachments": 0,
    "Importance": "normal",
    "MailboxSource": "Team4401@TDSynnex.com",
    "ThreadID": "AAQkAGUzODYyY2VhLWI4MGYtNDJiNC1hYWQyLTI2OGY1MmI4OTRhZgAQAJw93TkzEjdNi5LUK8VmZQE=",
    "ConversationID": "",
    "BodyHTML": null,
    "IsRead": 0,
    "ExtractedAt": "2025-05-21T11:52:21.217073",
    "AnalyzedAt": null,
    "SuggestedThemes": null,
    "SuggestedCategory": null,
    "KeyPhrases": null,
    "FullAnalysis": null,
    "IsSynthetic": 0,
    "workflow_state": null
  }
]