[
  {
    "MessageID": "AAMkAGUzODYyY2VhLWI4MGYtNDJiNC1hYWQyLTI2OGY1MmI4OTRhZgBGAAAAAAD2xIHfYeghS7NTr5D79J_KBwCpc6rLDJ0XTqvTzc3Yp-jsAAAAAAEKAACpc6rLDJ0XTqvTzc3Yp-jsAALUA9BgAAA=",
    "Subject": "Sales EDI PO UPLOAD Alert (US)",
    "SenderEmail": "b2b@synnex.com",
    "SenderName": "B2B",
    "Recipients": "{\"to\": [\"team4401@tdsynnex.com\"], \"cc\": []}",
    "ReceivedTime": "2025-04-04T17:05:15Z",
    "FolderPath": "Deleted Items",
    "BodyText": "[External E-mail] CAUTION: This email originated from outside of the organization. Do not click links or open attachments unless you recognize the sender and know the content is safe.\r\n\r\n\r\n                         \r\n ----------------------- \r\n **CUST850 NOT UPLOADED: \r\n\r\n tp_name          created                        alert_desc                                                                       \r\n ---------------- ------------------------------ -------------------------------------------------------------------------------- \r\n COMPUTACENTER UN 04/04 09:35                    CUST850 NOT UPLOADED:TP NAME-COMPUTACENTER UNITEDPO#-~4507764406                 \r\n B&H FOTO AND ELE 04/04 09:35                    CUST850 NOT UPLOADED:TP NAME-B&H FOTO AND ELECTROPO#-~JB250404438R               \r\n CDW LOGISTICS    04/04 09:05                    CUST850 NOT UPLOADED:TP NAME-CDW LOGISTICSPO#-~CHF1072                           \r\n HITACHI AMERICA  04/01 12:05                    CUST850 NOT UPLOADED:TP NAME-HITACHI AMERICA LTDPO#-~396464                      \r\n\r\n                     \r\n ------------------- \r\n **NO 856 GENERATED: \r\n\r\n tp_name          created                        alert_desc                                                                       \r\n ---------------- ------------------------------ -------------------------------------------------------------------------------- \r\n CDW856           04/04 03:35                    NO 856 GENERATED:57371~order_no 157087647                                        \r\n CDW856           04/04 03:35                    NO 856 GENERATED:57371~order_no 157230604                                        \r\n CDW856           04/04 03:35                    NO 856 GENERATED:57371~order_no 159023493                                        \r\n CDW856           04/04 03:35                    NO 856 GENERATED:57371~order_no 159029688                                        \r\n[... content truncated for analysis ...]",
    "HasAttachments": 0,
    "Importance": "normal",
    "MailboxSource": "Team4401@TDSynnex.com",
    "ThreadID": "AAQkAGUzODYyY2VhLWI4MGYtNDJiNC1hYWQyLTI2OGY1MmI4OTRhZgAQAJSTLeD-DhJLtSk-bKD-gVc=",
    "ConversationID": "",
    "BodyHTML": null,
    "IsRead": 0,
    "ExtractedAt": "2025-05-21T11:53:03.159743",
    "AnalyzedAt": null,
    "SuggestedThemes": null,
    "SuggestedCategory": null,
    "KeyPhrases": null,
    "FullAnalysis": null,
    "IsSynthetic": 0,
    "workflow_state": null
  },
  {
    "MessageID": "AAMkAGUzODYyY2VhLWI4MGYtNDJiNC1hYWQyLTI2OGY1MmI4OTRhZgBGAAAAAAD2xIHfYeghS7NTr5D79J_KBwCpc6rLDJ0XTqvTzc3Yp-jsAAAAAAEKAACpc6rLDJ0XTqvTzc3Yp-jsAALUA9BfAAA=",
    "Subject": "Sales EDI PO UPLOAD Alert (US)",
    "SenderEmail": "b2b@synnex.com",
    "SenderName": "B2B",
    "Recipients": "{\"to\": [\"team4401@tdsynnex.com\"], \"cc\": []}",
    "ReceivedTime": "2025-04-04T16:35:22Z",
    "FolderPath": "Deleted Items",
    "BodyText": "[External E-mail] CAUTION: This email originated from outside of the organization. Do not click links or open attachments unless you recognize the sender and know the content is safe.\r\n\r\n\r\n                         \r\n ----------------------- \r\n **CUST850 NOT UPLOADED: \r\n\r\n tp_name          created                        alert_desc                                                                       \r\n ---------------- ------------------------------ -------------------------------------------------------------------------------- \r\n CDW LOGISTICS    04/04 09:05                    CUST850 NOT UPLOADED:TP NAME-CDW LOGISTICSPO#-~CHF1072                           \r\n HITACHI AMERICA  04/01 12:05                    CUST850 NOT UPLOADED:TP NAME-HITACHI AMERICA LTDPO#-~396464                      \r\n\r\n                     \r\n ------------------- \r\n **NO 856 GENERATED: \r\n\r\n tp_name          created                        alert_desc                                                                       \r\n ---------------- ------------------------------ -------------------------------------------------------------------------------- \r\n CDW856           04/04 03:35                    NO 856 GENERATED:57371~order_no 157087647                                        \r\n CDW856           04/04 03:35                    NO 856 GENERATED:57371~order_no 157230604                                        \r\n CDW856           04/04 03:35                    NO 856 GENERATED:57371~order_no 159023493                                        \r\n CDW856           04/04 03:35                    NO 856 GENERATED:57371~order_no 159029688                                        \r\n CDW856           04/04 03:35                    NO 856 GENERATED:57371~order_no 159121473                                        \r\n CDW856           04/04 03:35                    NO 856 GENERATED:57371~order_no 159289147                                        \r\n[... content truncated for analysis ...]",
    "HasAttachments": 0,
    "Importance": "normal",
    "MailboxSource": "Team4401@TDSynnex.com",
    "ThreadID": "AAQkAGUzODYyY2VhLWI4MGYtNDJiNC1hYWQyLTI2OGY1MmI4OTRhZgAQALna41_SthRIllUnOxAWiP8=",
    "ConversationID": "",
    "BodyHTML": null,
    "IsRead": 0,
    "ExtractedAt": "2025-05-21T11:53:03.170398",
    "AnalyzedAt": null,
    "SuggestedThemes": null,
    "SuggestedCategory": null,
    "KeyPhrases": null,
    "FullAnalysis": null,
    "IsSynthetic": 0,
    "workflow_state": null
  },
  {
    "MessageID": "AAMkAGUzODYyY2VhLWI4MGYtNDJiNC1hYWQyLTI2OGY1MmI4OTRhZgBGAAAAAAD2xIHfYeghS7NTr5D79J_KBwCpc6rLDJ0XTqvTzc3Yp-jsAAAAAAEKAACpc6rLDJ0XTqvTzc3Yp-jsAAGFofUkAAA=",
    "Subject": "Increase Customer Loyalty With Personalized Service",
    "SenderEmail": "customerservice@lorman.com",
    "SenderName": "Lorman Education",
    "Recipients": "{\"to\": [\"Clark.Morada@tdsynnex.com\"], \"cc\": []}",
    "ReceivedTime": "2025-04-04T16:10:51Z",
    "FolderPath": "Deleted Items",
    "BodyText": "<html><head>\r\n<meta http-equiv=\"Content-Type\" content=\"text/html; charset=utf-8\"><meta name=\"viewport\" content=\"width=device-width, initialscale=1.0\"><meta content=\"IE=edge\"><style type=\"text/css\">\r\n<!--\r\n@media screen and (max-width: 480px) {\r\nslot[style]\r\n\t{margin-right:0!important}\r\n.columnDiv\r\n\t{margin-right:0!important}\r\n\r\n\t}\r\n-->\r\n</style><style type=\"text/css\">\r\n<!--\r\n.contentpageDefaultEmailContentPageTemplate .contentRoot\r\n\t{width:600px}\r\n@media only screen and (max-width: 480px) {\r\n.contentpageDefaultEmailContentPageTemplate .contentRoot\r\n\t{width:320px}\r\n\r\n\t}\r\n-->\r\n</style><style type=\"text/css\">\r\n<!--\r\n@media screen and (max-width: 480px) {\r\n.contentbuilderBaseColumnRow .columnCell\r\n\t{display:inline-block;\r\n\twidth:100%}\r\n\r\n\t}\r\n-->\r\n[... content truncated for analysis ...]",
    "HasAttachments": 0,
    "Importance": "normal",
    "MailboxSource": "Team4401@TDSynnex.com",
    "ThreadID": "AAQkAGUzODYyY2VhLWI4MGYtNDJiNC1hYWQyLTI2OGY1MmI4OTRhZgAQANNylRBjNFhPuJJObgryyE4=",
    "ConversationID": "",
    "BodyHTML": null,
    "IsRead": 0,
    "ExtractedAt": "2025-05-21T11:53:03.181627",
    "AnalyzedAt": null,
    "SuggestedThemes": null,
    "SuggestedCategory": null,
    "KeyPhrases": null,
    "FullAnalysis": null,
    "IsSynthetic": 0,
    "workflow_state": null
  },
  {
    "MessageID": "AAMkAGUzODYyY2VhLWI4MGYtNDJiNC1hYWQyLTI2OGY1MmI4OTRhZgBGAAAAAAD2xIHfYeghS7NTr5D79J_KBwCpc6rLDJ0XTqvTzc3Yp-jsAAAAAAEKAACpc6rLDJ0XTqvTzc3Yp-jsAALUA9BeAAA=",
    "Subject": "Sales EDI PO UPLOAD Alert (US)",
    "SenderEmail": "b2b@synnex.com",
    "SenderName": "B2B",
    "Recipients": "{\"to\": [\"team4401@tdsynnex.com\"], \"cc\": []}",
    "ReceivedTime": "2025-04-04T16:05:19Z",
    "FolderPath": "Deleted Items",
    "BodyText": "[External E-mail] CAUTION: This email originated from outside of the organization. Do not click links or open attachments unless you recognize the sender and know the content is safe.\r\n\r\n\r\n                         \r\n ----------------------- \r\n **CUST850 NOT UPLOADED: \r\n\r\n tp_name          created                        alert_desc                                                                       \r\n ---------------- ------------------------------ -------------------------------------------------------------------------------- \r\n HITACHI AMERICA  04/01 12:05                    CUST850 NOT UPLOADED:TP NAME-HITACHI AMERICA LTDPO#-~396464                      \r\n\r\n                     \r\n ------------------- \r\n **NO 856 GENERATED: \r\n\r\n tp_name          created                        alert_desc                                                                       \r\n ---------------- ------------------------------ -------------------------------------------------------------------------------- \r\n CDW856           04/04 03:35                    NO 856 GENERATED:57371~order_no 157087647                                        \r\n CDW856           04/04 03:35                    NO 856 GENERATED:57371~order_no 157230604                                        \r\n CDW856           04/04 03:35                    NO 856 GENERATED:57371~order_no 159023493                                        \r\n CDW856           04/04 03:35                    NO 856 GENERATED:57371~order_no 159029688                                        \r\n CDW856           04/04 03:35                    NO 856 GENERATED:57371~order_no 159121473                                        \r\n CDW856           04/04 03:35                    NO 856 GENERATED:57371~order_no 159289147                                        \r\n CDW856           04/04 03:35                    NO 856 GENERATED:57371~order_no 159492644                                        \r\n[... content truncated for analysis ...]",
    "HasAttachments": 0,
    "Importance": "normal",
    "MailboxSource": "Team4401@TDSynnex.com",
    "ThreadID": "AAQkAGUzODYyY2VhLWI4MGYtNDJiNC1hYWQyLTI2OGY1MmI4OTRhZgAQANOxPI6x8SJHh4yQE0K_ewE=",
    "ConversationID": "",
    "BodyHTML": null,
    "IsRead": 0,
    "ExtractedAt": "2025-05-21T11:53:03.187002",
    "AnalyzedAt": null,
    "SuggestedThemes": null,
    "SuggestedCategory": null,
    "KeyPhrases": null,
    "FullAnalysis": null,
    "IsSynthetic": 0,
    "workflow_state": null
  },
  {
    "MessageID": "AAMkAGUzODYyY2VhLWI4MGYtNDJiNC1hYWQyLTI2OGY1MmI4OTRhZgBGAAAAAAD2xIHfYeghS7NTr5D79J_KBwCpc6rLDJ0XTqvTzc3Yp-jsAAAAAAEKAACpc6rLDJ0XTqvTzc3Yp-jsAALUA9BdAAA=",
    "Subject": "Sales EDI PO UPLOAD Alert (US)",
    "SenderEmail": "b2b@synnex.com",
    "SenderName": "B2B",
    "Recipients": "{\"to\": [\"team4401@tdsynnex.com\"], \"cc\": []}",
    "ReceivedTime": "2025-04-04T15:35:14Z",
    "FolderPath": "Deleted Items",
    "BodyText": "[External E-mail] CAUTION: This email originated from outside of the organization. Do not click links or open attachments unless you recognize the sender and know the content is safe.\r\n\r\n\r\n                         \r\n ----------------------- \r\n **CUST850 NOT UPLOADED: \r\n\r\n tp_name          created                        alert_desc                                                                       \r\n ---------------- ------------------------------ -------------------------------------------------------------------------------- \r\n HITACHI AMERICA  04/01 12:05                    CUST850 NOT UPLOADED:TP NAME-HITACHI AMERICA LTDPO#-~396464                      \r\n\r\n                     \r\n ------------------- \r\n **NO 856 GENERATED: \r\n\r\n tp_name          created                        alert_desc                                                                       \r\n ---------------- ------------------------------ -------------------------------------------------------------------------------- \r\n CDW856           04/04 03:35                    NO 856 GENERATED:57371~order_no 157087647                                        \r\n CDW856           04/04 03:35                    NO 856 GENERATED:57371~order_no 157230604                                        \r\n CDW856           04/04 03:35                    NO 856 GENERATED:57371~order_no 159023493                                        \r\n CDW856           04/04 03:35                    NO 856 GENERATED:57371~order_no 159029688                                        \r\n CDW856           04/04 03:35                    NO 856 GENERATED:57371~order_no 159121473                                        \r\n CDW856           04/04 03:35                    NO 856 GENERATED:57371~order_no 159289147                                        \r\n CDW856           04/04 03:35                    NO 856 GENERATED:57371~order_no 159492644                                        \r\n[... content truncated for analysis ...]",
    "HasAttachments": 0,
    "Importance": "normal",
    "MailboxSource": "Team4401@TDSynnex.com",
    "ThreadID": "AAQkAGUzODYyY2VhLWI4MGYtNDJiNC1hYWQyLTI2OGY1MmI4OTRhZgAQAGpwdhOMD7dDm9u7RrRLiJs=",
    "ConversationID": "",
    "BodyHTML": null,
    "IsRead": 0,
    "ExtractedAt": "2025-05-21T11:53:03.197185",
    "AnalyzedAt": null,
    "SuggestedThemes": null,
    "SuggestedCategory": null,
    "KeyPhrases": null,
    "FullAnalysis": null,
    "IsSynthetic": 0,
    "workflow_state": null
  },
  {
    "MessageID": "AAMkAGUzODYyY2VhLWI4MGYtNDJiNC1hYWQyLTI2OGY1MmI4OTRhZgBGAAAAAAD2xIHfYeghS7NTr5D79J_KBwCpc6rLDJ0XTqvTzc3Yp-jsAAAAAAEKAACpc6rLDJ0XTqvTzc3Yp-jsAALUA9BcAAA=",
    "Subject": "Sales EDI PO UPLOAD Alert (US)",
    "SenderEmail": "b2b@synnex.com",
    "SenderName": "B2B",
    "Recipients": "{\"to\": [\"team4401@tdsynnex.com\"], \"cc\": []}",
    "ReceivedTime": "2025-04-04T15:05:20Z",
    "FolderPath": "Deleted Items",
    "BodyText": "[External E-mail] CAUTION: This email originated from outside of the organization. Do not click links or open attachments unless you recognize the sender and know the content is safe.\r\n\r\n\r\n                         \r\n ----------------------- \r\n **CUST850 NOT UPLOADED: \r\n\r\n tp_name          created                        alert_desc                                                                       \r\n ---------------- ------------------------------ -------------------------------------------------------------------------------- \r\n HITACHI AMERICA  04/01 12:05                    CUST850 NOT UPLOADED:TP NAME-HITACHI AMERICA LTDPO#-~396464                      \r\n\r\n                     \r\n ------------------- \r\n **NO 856 GENERATED: \r\n\r\n tp_name          created                        alert_desc                                                                       \r\n ---------------- ------------------------------ -------------------------------------------------------------------------------- \r\n CDW856           04/04 03:35                    NO 856 GENERATED:57371~order_no 157087647                                        \r\n CDW856           04/04 03:35                    NO 856 GENERATED:57371~order_no 157230604                                        \r\n CDW856           04/04 03:35                    NO 856 GENERATED:57371~order_no 159023493                                        \r\n CDW856           04/04 03:35                    NO 856 GENERATED:57371~order_no 159029688                                        \r\n CDW856           04/04 03:35                    NO 856 GENERATED:57371~order_no 159121473                                        \r\n CDW856           04/04 03:35                    NO 856 GENERATED:57371~order_no 159289147                                        \r\n CDW856           04/04 03:35                    NO 856 GENERATED:57371~order_no 159492644                                        \r\n[... content truncated for analysis ...]",
    "HasAttachments": 0,
    "Importance": "normal",
    "MailboxSource": "Team4401@TDSynnex.com",
    "ThreadID": "AAQkAGUzODYyY2VhLWI4MGYtNDJiNC1hYWQyLTI2OGY1MmI4OTRhZgAQAGMNHQq1HbxCpDUASaaDO-Y=",
    "ConversationID": "",
    "BodyHTML": null,
    "IsRead": 0,
    "ExtractedAt": "2025-05-21T11:53:03.206764",
    "AnalyzedAt": null,
    "SuggestedThemes": null,
    "SuggestedCategory": null,
    "KeyPhrases": null,
    "FullAnalysis": null,
    "IsSynthetic": 0,
    "workflow_state": null
  },
  {
    "MessageID": "AAMkAGUzODYyY2VhLWI4MGYtNDJiNC1hYWQyLTI2OGY1MmI4OTRhZgBGAAAAAAD2xIHfYeghS7NTr5D79J_KBwCpc6rLDJ0XTqvTzc3Yp-jsAAAAAAEKAACpc6rLDJ0XTqvTzc3Yp-jsAALUA9BbAAA=",
    "Subject": "Sales EDI PO UPLOAD Alert (US)",
    "SenderEmail": "b2b@synnex.com",
    "SenderName": "B2B",
    "Recipients": "{\"to\": [\"team4401@tdsynnex.com\"], \"cc\": []}",
    "ReceivedTime": "2025-04-04T14:35:23Z",
    "FolderPath": "Deleted Items",
    "BodyText": "[External E-mail] CAUTION: This email originated from outside of the organization. Do not click links or open attachments unless you recognize the sender and know the content is safe.\r\n\r\n\r\n                         \r\n ----------------------- \r\n **CUST850 NOT UPLOADED: \r\n\r\n tp_name          created                        alert_desc                                                                       \r\n ---------------- ------------------------------ -------------------------------------------------------------------------------- \r\n HITACHI AMERICA  04/01 12:05                    CUST850 NOT UPLOADED:TP NAME-HITACHI AMERICA LTDPO#-~396464                      \r\n\r\n                     \r\n ------------------- \r\n **NO 856 GENERATED: \r\n\r\n tp_name          created                        alert_desc                                                                       \r\n ---------------- ------------------------------ -------------------------------------------------------------------------------- \r\n CDW856           04/04 03:35                    NO 856 GENERATED:57371~order_no 157087647                                        \r\n CDW856           04/04 03:35                    NO 856 GENERATED:57371~order_no 157230604                                        \r\n CDW856           04/04 03:35                    NO 856 GENERATED:57371~order_no 159023493                                        \r\n CDW856           04/04 03:35                    NO 856 GENERATED:57371~order_no 159029688                                        \r\n CDW856           04/04 03:35                    NO 856 GENERATED:57371~order_no 159121473                                        \r\n CDW856           04/04 03:35                    NO 856 GENERATED:57371~order_no 159289147                                        \r\n CDW856           04/04 03:35                    NO 856 GENERATED:57371~order_no 159492644                                        \r\n[... content truncated for analysis ...]",
    "HasAttachments": 0,
    "Importance": "normal",
    "MailboxSource": "Team4401@TDSynnex.com",
    "ThreadID": "AAQkAGUzODYyY2VhLWI4MGYtNDJiNC1hYWQyLTI2OGY1MmI4OTRhZgAQALsrfQZnjHtCmq_Jw-YAmpU=",
    "ConversationID": "",
    "BodyHTML": null,
    "IsRead": 0,
    "ExtractedAt": "2025-05-21T11:53:03.216799",
    "AnalyzedAt": null,
    "SuggestedThemes": null,
    "SuggestedCategory": null,
    "KeyPhrases": null,
    "FullAnalysis": null,
    "IsSynthetic": 0,
    "workflow_state": null
  },
  {
    "MessageID": "AAMkAGUzODYyY2VhLWI4MGYtNDJiNC1hYWQyLTI2OGY1MmI4OTRhZgBGAAAAAAD2xIHfYeghS7NTr5D79J_KBwCpc6rLDJ0XTqvTzc3Yp-jsAAAAAAEKAACpc6rLDJ0XTqvTzc3Yp-jsAALUA9BaAAA=",
    "Subject": "Sales EDI PO UPLOAD Alert (US)",
    "SenderEmail": "b2b@synnex.com",
    "SenderName": "B2B",
    "Recipients": "{\"to\": [\"team4401@tdsynnex.com\"], \"cc\": []}",
    "ReceivedTime": "2025-04-04T14:05:22Z",
    "FolderPath": "Deleted Items",
    "BodyText": "[External E-mail] CAUTION: This email originated from outside of the organization. Do not click links or open attachments unless you recognize the sender and know the content is safe.\r\n\r\n\r\n                         \r\n ----------------------- \r\n **CUST850 NOT UPLOADED: \r\n\r\n tp_name          created                        alert_desc                                                                       \r\n ---------------- ------------------------------ -------------------------------------------------------------------------------- \r\n HITACHI AMERICA  04/01 12:05                    CUST850 NOT UPLOADED:TP NAME-HITACHI AMERICA LTDPO#-~396464                      \r\n\r\n                     \r\n ------------------- \r\n **NO 856 GENERATED: \r\n\r\n tp_name          created                        alert_desc                                                                       \r\n ---------------- ------------------------------ -------------------------------------------------------------------------------- \r\n CDW856           04/04 03:35                    NO 856 GENERATED:57371~order_no 157087647                                        \r\n CDW856           04/04 03:35                    NO 856 GENERATED:57371~order_no 157230604                                        \r\n CDW856           04/04 03:35                    NO 856 GENERATED:57371~order_no 159023493                                        \r\n CDW856           04/04 03:35                    NO 856 GENERATED:57371~order_no 159029688                                        \r\n CDW856           04/04 03:35                    NO 856 GENERATED:57371~order_no 159121473                                        \r\n CDW856           04/04 03:35                    NO 856 GENERATED:57371~order_no 159289147                                        \r\n CDW856           04/04 03:35                    NO 856 GENERATED:57371~order_no 159492644                                        \r\n[... content truncated for analysis ...]",
    "HasAttachments": 0,
    "Importance": "normal",
    "MailboxSource": "Team4401@TDSynnex.com",
    "ThreadID": "AAQkAGUzODYyY2VhLWI4MGYtNDJiNC1hYWQyLTI2OGY1MmI4OTRhZgAQAFLV-rPK0-xEpKWW7r_oH68=",
    "ConversationID": "",
    "BodyHTML": null,
    "IsRead": 0,
    "ExtractedAt": "2025-05-21T11:53:03.227867",
    "AnalyzedAt": null,
    "SuggestedThemes": null,
    "SuggestedCategory": null,
    "KeyPhrases": null,
    "FullAnalysis": null,
    "IsSynthetic": 0,
    "workflow_state": null
  },
  {
    "MessageID": "AAMkAGUzODYyY2VhLWI4MGYtNDJiNC1hYWQyLTI2OGY1MmI4OTRhZgBGAAAAAAD2xIHfYeghS7NTr5D79J_KBwCpc6rLDJ0XTqvTzc3Yp-jsAAAAAAEKAACpc6rLDJ0XTqvTzc3Yp-jsAALUA9BZAAA=",
    "Subject": "Sales EDI PO UPLOAD Alert (US)",
    "SenderEmail": "b2b@synnex.com",
    "SenderName": "B2B",
    "Recipients": "{\"to\": [\"team4401@tdsynnex.com\"], \"cc\": []}",
    "ReceivedTime": "2025-04-04T13:35:16Z",
    "FolderPath": "Deleted Items",
    "BodyText": "[External E-mail] CAUTION: This email originated from outside of the organization. Do not click links or open attachments unless you recognize the sender and know the content is safe.\r\n\r\n\r\n                         \r\n ----------------------- \r\n **CUST850 NOT UPLOADED: \r\n\r\n tp_name          created                        alert_desc                                                                       \r\n ---------------- ------------------------------ -------------------------------------------------------------------------------- \r\n HITACHI AMERICA  04/01 12:05                    CUST850 NOT UPLOADED:TP NAME-HITACHI AMERICA LTDPO#-~396464                      \r\n\r\n                     \r\n ------------------- \r\n **NO 856 GENERATED: \r\n\r\n tp_name          created                        alert_desc                                                                       \r\n ---------------- ------------------------------ -------------------------------------------------------------------------------- \r\n CDW856           04/04 03:35                    NO 856 GENERATED:57371~order_no 157087647                                        \r\n CDW856           04/04 03:35                    NO 856 GENERATED:57371~order_no 157230604                                        \r\n CDW856           04/04 03:35                    NO 856 GENERATED:57371~order_no 159023493                                        \r\n CDW856           04/04 03:35                    NO 856 GENERATED:57371~order_no 159029688                                        \r\n CDW856           04/04 03:35                    NO 856 GENERATED:57371~order_no 159121473                                        \r\n CDW856           04/04 03:35                    NO 856 GENERATED:57371~order_no 159289147                                        \r\n CDW856           04/04 03:35                    NO 856 GENERATED:57371~order_no 159492644                                        \r\n[... content truncated for analysis ...]",
    "HasAttachments": 0,
    "Importance": "normal",
    "MailboxSource": "Team4401@TDSynnex.com",
    "ThreadID": "AAQkAGUzODYyY2VhLWI4MGYtNDJiNC1hYWQyLTI2OGY1MmI4OTRhZgAQAB673hrhqd9Phb5a6lB5LXY=",
    "ConversationID": "",
    "BodyHTML": null,
    "IsRead": 0,
    "ExtractedAt": "2025-05-21T11:53:03.237738",
    "AnalyzedAt": null,
    "SuggestedThemes": null,
    "SuggestedCategory": null,
    "KeyPhrases": null,
    "FullAnalysis": null,
    "IsSynthetic": 0,
    "workflow_state": null
  },
  {
    "MessageID": "AAMkAGUzODYyY2VhLWI4MGYtNDJiNC1hYWQyLTI2OGY1MmI4OTRhZgBGAAAAAAD2xIHfYeghS7NTr5D79J_KBwCpc6rLDJ0XTqvTzc3Yp-jsAAAAAAEKAACpc6rLDJ0XTqvTzc3Yp-jsAALUA9BYAAA=",
    "Subject": "Sales EDI PO UPLOAD Alert (US)",
    "SenderEmail": "b2b@synnex.com",
    "SenderName": "B2B",
    "Recipients": "{\"to\": [\"team4401@tdsynnex.com\"], \"cc\": []}",
    "ReceivedTime": "2025-04-04T13:05:17Z",
    "FolderPath": "Deleted Items",
    "BodyText": "[External E-mail] CAUTION: This email originated from outside of the organization. Do not click links or open attachments unless you recognize the sender and know the content is safe.\r\n\r\n\r\n                         \r\n ----------------------- \r\n **CUST850 NOT UPLOADED: \r\n\r\n tp_name          created                        alert_desc                                                                       \r\n ---------------- ------------------------------ -------------------------------------------------------------------------------- \r\n HITACHI AMERICA  04/01 12:05                    CUST850 NOT UPLOADED:TP NAME-HITACHI AMERICA LTDPO#-~396464                      \r\n\r\n                     \r\n ------------------- \r\n **NO 856 GENERATED: \r\n\r\n tp_name          created                        alert_desc                                                                       \r\n ---------------- ------------------------------ -------------------------------------------------------------------------------- \r\n CDW856           04/04 03:35                    NO 856 GENERATED:57371~order_no 157087647                                        \r\n CDW856           04/04 03:35                    NO 856 GENERATED:57371~order_no 157230604                                        \r\n CDW856           04/04 03:35                    NO 856 GENERATED:57371~order_no 159023493                                        \r\n CDW856           04/04 03:35                    NO 856 GENERATED:57371~order_no 159029688                                        \r\n CDW856           04/04 03:35                    NO 856 GENERATED:57371~order_no 159121473                                        \r\n CDW856           04/04 03:35                    NO 856 GENERATED:57371~order_no 159289147                                        \r\n CDW856           04/04 03:35                    NO 856 GENERATED:57371~order_no 159492644                                        \r\n[... content truncated for analysis ...]",
    "HasAttachments": 0,
    "Importance": "normal",
    "MailboxSource": "Team4401@TDSynnex.com",
    "ThreadID": "AAQkAGUzODYyY2VhLWI4MGYtNDJiNC1hYWQyLTI2OGY1MmI4OTRhZgAQAEHQsWqzJO1KvXRkupHqo_0=",
    "ConversationID": "",
    "BodyHTML": null,
    "IsRead": 0,
    "ExtractedAt": "2025-05-21T11:53:03.249280",
    "AnalyzedAt": null,
    "SuggestedThemes": null,
    "SuggestedCategory": null,
    "KeyPhrases": null,
    "FullAnalysis": null,
    "IsSynthetic": 0,
    "workflow_state": null
  }
]